chartstag/__init__.py
chartstag/mermaid/__init__.py
chartstag/mermaid/data/mermaid_min.zip
chartstag-0.8.2.dist-info/LICENSE
chartstag-0.8.2.dist-info/METADATA
chartstag-0.8.2.dist-info/WHEEL
chartstag-0.8.2.dist-info/RECORD
