Metadata-Version: 2.1
Name: chartstag
Version: 0.8.2
Summary: Charting and diagram extension for SciStag
Home-page: https://github.com/scistag/chartstag
License: MIT
Keywords: Data Science,Data Engineering,Data Visualization
Author: Michael Ikemann
Requires-Python: >=3.9
Classifier: Intended Audience :: Developers
Classifier: License :: OSI Approved :: MIT License
Classifier: Operating System :: OS Independent
Classifier: Programming Language :: Python
Classifier: Programming Language :: Python :: 3
Classifier: Programming Language :: Python :: 3.9
Classifier: Programming Language :: Python :: 3.10
Classifier: Programming Language :: Python :: 3.11
Classifier: Programming Language :: Python :: 3.12
Classifier: Topic :: Software Development :: Libraries :: Python Modules
Project-URL: Documentation, https://scistag.readthedocs.io
Project-URL: Repository, https://github.com/scistag/chartstag
